{
  "name": "Tori Bogenschutz",
  "gender": "F",
  "age": "18",
  "id": 72983,
  "events": {
    "3 Meter": {
      "Front": {
        "dives": {
          "101C": {
            "dd": 1.4,
            "height": "3",
            "performance": [
              {
                "date": "2021-03-06",
                "score": 22.05,
                "meet": "2021 Schroeder March Invite"
              }
            ],
            "count": 1,
            "average_score": 22.05
          },
          "103B": {
            "dd": 1.6,
            "height": "3",
            "performance": [
              {
                "date": "2021-03-06",
                "score": 28.8,
                "meet": "2021 Schroeder March Invite"
              }
            ],
            "count": 1,
            "average_score": 28.8
          }
        }
      },
      "Back": {
        "dives": {
          "201B": {
            "dd": 1.8,
            "height": "3",
            "performance": [
              {
                "date": "2021-03-06",
                "score": 28.35,
                "meet": "2021 Schroeder March Invite"
              }
            ],
            "count": 1,
            "average_score": 28.35
          },
          "202A": {
            "dd": 1.8,
            "height": "3",
            "performance": [
              {
                "date": "2021-03-06",
                "score": 29.7,
                "meet": "2021 Schroeder March Invite"
              }
            ],
            "count": 1,
            "average_score": 29.7
          }
        }
      },
      "Reverse": {
        "dives": {
          "301C": {
            "dd": 1.8,
            "height": "3",
            "performance": [
              {
                "date": "2021-03-06",
                "score": 32.4,
                "meet": "2021 Schroeder March Invite"
              }
            ],
            "count": 1,
            "average_score": 32.4
          },
          "302C": {
            "dd": 1.7,
            "height": "3",
            "performance": [
              {
                "date": "2021-03-06",
                "score": 30.6,
                "meet": "2021 Schroeder March Invite"
              }
            ],
            "count": 1,
            "average_score": 30.6
          }
        }
      },
      "Inward": {
        "dives": {
          "401B": {
            "dd": 1.4,
            "height": "3",
            "performance": [
              {
                "date": "2021-03-06",
                "score": 22.05,
                "meet": "2021 Schroeder March Invite"
              }
            ],
            "count": 1,
            "average_score": 22.05
          },
          "403C": {
            "dd": 1.9,
            "height": "3",
            "performance": [
              {
                "date": "2021-03-06",
                "score": 32.78,
                "meet": "2021 Schroeder March Invite"
              }
            ],
            "count": 1,
            "average_score": 32.78
          }
        }
      },
      "Twister": {
        "dives": {
          "5132D": {
            "dd": 2.1,
            "height": "3",
            "performance": [
              {
                "date": "2021-03-06",
                "score": 36.23,
                "meet": "2021 Schroeder March Invite"
              }
            ],
            "count": 1,
            "average_score": 36.23
          },
          "5231D": {
            "dd": 2.0,
            "height": "3",
            "performance": [
              {
                "date": "2021-03-06",
                "score": 31.5,
                "meet": "2021 Schroeder March Invite"
              }
            ],
            "count": 1,
            "average_score": 31.5
          }
        }
      }
    },
    "1 Meter": {
      "Front": {
        "dives": {
          "103B": {
            "dd": 1.7,
            "height": "1",
            "performance": [
              {
                "date": "2022-01-22",
                "score": 31.88,
                "meet": "2022 Schroeder Winter Invite"
              },
              {
                "date": "2021-04-16",
                "score": 28.05,
                "meet": "2021 Schroeder April Invite"
              }
            ],
            "count": 2,
            "average_score": 29.96
          },
          "104C": {
            "dd": 2.2,
            "height": "1",
            "performance": [
              {
                "date": "2022-01-22",
                "score": 26.4,
                "meet": "2022 Schroeder Winter Invite"
              },
              {
                "date": "2021-04-16",
                "score": 28.05,
                "meet": "2021 Schroeder April Invite"
              }
            ],
            "count": 2,
            "average_score": 27.23
          }
        }
      },
      "Back": {
        "dives": {
          "201B": {
            "dd": 1.6,
            "height": "1",
            "performance": [
              {
                "date": "2022-01-22",
                "score": 28.8,
                "meet": "2022 Schroeder Winter Invite"
              },
              {
                "date": "2021-04-16",
                "score": 26.4,
                "meet": "2021 Schroeder April Invite"
              }
            ],
            "count": 2,
            "average_score": 27.6
          },
          "203B": {
            "dd": 2.3,
            "height": "1",
            "performance": [
              {
                "date": "2022-01-22",
                "score": 34.5,
                "meet": "2022 Schroeder Winter Invite"
              }
            ],
            "count": 1,
            "average_score": 34.5
          },
          "203C": {
            "dd": 2.0,
            "height": "1",
            "performance": [
              {
                "date": "2021-04-16",
                "score": 28.5,
                "meet": "2021 Schroeder April Invite"
              }
            ],
            "count": 1,
            "average_score": 28.5
          }
        }
      },
      "Reverse": {
        "dives": {
          "301B": {
            "dd": 1.7,
            "height": "1",
            "performance": [
              {
                "date": "2022-01-22",
                "score": 17.85,
                "meet": "2022 Schroeder Winter Invite"
              }
            ],
            "count": 1,
            "average_score": 17.85
          },
          "301C": {
            "dd": 1.6,
            "height": "1",
            "performance": [
              {
                "date": "2021-04-16",
                "score": 20.4,
                "meet": "2021 Schroeder April Invite"
              }
            ],
            "count": 1,
            "average_score": 20.4
          },
          "302C": {
            "dd": 1.6,
            "height": "1",
            "performance": [
              {
                "date": "2022-01-22",
                "score": 25.2,
                "meet": "2022 Schroeder Winter Invite"
              },
              {
                "date": "2021-04-16",
                "score": 22.8,
                "meet": "2021 Schroeder April Invite"
              }
            ],
            "count": 2,
            "average_score": 24.0
          }
        }
      },
      "Inward": {
        "dives": {
          "401B": {
            "dd": 1.5,
            "height": "1",
            "performance": [
              {
                "date": "2022-01-22",
                "score": 25.88,
                "meet": "2022 Schroeder Winter Invite"
              },
              {
                "date": "2021-04-16",
                "score": 27.0,
                "meet": "2021 Schroeder April Invite"
              }
            ],
            "count": 2,
            "average_score": 26.44
          },
          "403C": {
            "dd": 2.2,
            "height": "1",
            "performance": [
              {
                "date": "2022-01-22",
                "score": 29.7,
                "meet": "2022 Schroeder Winter Invite"
              },
              {
                "date": "2021-04-16",
                "score": 36.3,
                "meet": "2021 Schroeder April Invite"
              }
            ],
            "count": 2,
            "average_score": 33.0
          }
        }
      },
      "Twister": {
        "dives": {
          "5122D": {
            "dd": 1.9,
            "height": "1",
            "performance": [
              {
                "date": "2021-04-16",
                "score": 24.23,
                "meet": "2021 Schroeder April Invite"
              }
            ],
            "count": 1,
            "average_score": 24.23
          },
          "5124D": {
            "dd": 2.3,
            "height": "1",
            "performance": [
              {
                "date": "2022-01-22",
                "score": 32.78,
                "meet": "2022 Schroeder Winter Invite"
              }
            ],
            "count": 1,
            "average_score": 32.78
          },
          "5231D": {
            "dd": 2.1,
            "height": "1",
            "performance": [
              {
                "date": "2022-01-22",
                "score": 34.65,
                "meet": "2022 Schroeder Winter Invite"
              },
              {
                "date": "2021-04-16",
                "score": 29.93,
                "meet": "2021 Schroeder April Invite"
              }
            ],
            "count": 2,
            "average_score": 32.29
          }
        }
      }
    }
  },
  "rankings": {
    "3 Meter": {
      "Front": {
        "top_2_avg": 25.43,
        "best_dive_id": "103B",
        "best_dive_avg": 28.8,
        "grade": 3.2
      },
      "Back": {
        "top_2_avg": 29.02,
        "best_dive_id": "202A",
        "best_dive_avg": 29.7,
        "grade": 3.6
      },
      "Reverse": {
        "top_2_avg": 31.5,
        "best_dive_id": "301C",
        "best_dive_avg": 32.4,
        "grade": 3.9
      },
      "Inward": {
        "top_2_avg": 27.41,
        "best_dive_id": "403C",
        "best_dive_avg": 32.78,
        "grade": 3.4
      },
      "Twister": {
        "top_2_avg": 33.86,
        "best_dive_id": "5132D",
        "best_dive_avg": 36.23,
        "grade": 4.2
      },
      "average_grade": 3.7
    },
    "1 Meter": {
      "Front": {
        "top_2_avg": 28.59,
        "best_dive_id": "103B",
        "best_dive_avg": 29.96,
        "grade": 3.8
      },
      "Back": {
        "top_2_avg": 31.5,
        "best_dive_id": "203B",
        "best_dive_avg": 34.5,
        "grade": 4.2
      },
      "Reverse": {
        "top_2_avg": 22.8,
        "best_dive_id": "302C",
        "best_dive_avg": 24.0,
        "grade": 3.0
      },
      "Inward": {
        "top_2_avg": 29.72,
        "best_dive_id": "403C",
        "best_dive_avg": 33.0,
        "grade": 4.0
      },
      "Twister": {
        "top_2_avg": 32.45,
        "best_dive_id": "5124D",
        "best_dive_avg": 32.78,
        "grade": 4.3
      },
      "average_grade": 3.9
    },
    "overall_average_grade": 3.8
  }
}